{
  "timestamp": "2025-07-08T19:24:29.880Z",
  "summary": {
    "totalFiles": 2,
    "totalOriginalSize": "79.54 KB",
    "totalCleanedSize": "79.44 KB",
    "totalSizeSavings": "0.1%",
    "totalBytesRemoved": 106,
    "totalRejectedSelectors": 0
  },
  "files": [
    {
      "fileName": "styles.css",
      "cssFile": "/home/mhenke/Projects/mike-henke-website/styles.css",
      "backupFile": "/home/mhenke/Projects/mike-henke-website/styles.backup.css",
      "cleanedFile": "/home/mhenke/Projects/mike-henke-website/styles.cleaned.css",
      "originalSize": "56.98 KB",
      "cleanedSize": "56.88 KB",
      "sizeSavings": "0.2%",
      "bytesRemoved": 106,
      "rejectedSelectors": [],
      "rejectedCss": ""
    },
    {
      "fileName": "search.css",
      "cssFile": "/home/mhenke/Projects/mike-henke-website/assets/css/search.css",
      "backupFile": "/home/mhenke/Projects/mike-henke-website/assets/css/search.backup.css",
      "cleanedFile": "/home/mhenke/Projects/mike-henke-website/assets/css/search.cleaned.css",
      "originalSize": "22.56 KB",
      "cleanedSize": "22.56 KB",
      "sizeSavings": "0.0%",
      "bytesRemoved": 0,
      "rejectedSelectors": [],
      "rejectedCss": ""
    }
  ],
  "contentScanned": [
    "/home/mhenke/Projects/mike-henke-website/_site/**/*.html",
    "/home/mhenke/Projects/mike-henke-website/_includes/**/*.njk"
  ],
  "safelistUsed": [
    {},
    {},
    {},
    {},
    "hero-section",
    "hero-text",
    "hero-buttons",
    "hero-image",
    "skills-columns",
    "skills-card",
    "skill-row",
    "skill-label",
    "skill-percent",
    "progress-bar",
    "career-section",
    "career-timeline-grid",
    "timeline-col",
    "career-content-col",
    "timeline-step",
    "step-number",
    "step-line",
    "career-entry",
    "content-section-boxed",
    "section-title",
    "btn",
    "btn-primary",
    "btn-outline",
    "lang",
    {},
    "search-container",
    "search-input",
    "search-result",
    "result-categories",
    "category-tag",
    "reading-time",
    "search-icon",
    "search-wrapper",
    "active",
    "show",
    "hide",
    "visible",
    "hidden",
    {},
    {},
    {},
    {},
    "html",
    "body",
    "h1",
    "h2",
    "h3",
    "h4",
    "h5",
    "h6",
    "p",
    "a",
    "img",
    "div",
    "span",
    "header",
    "main",
    "section",
    "footer",
    "nav",
    "article",
    "aside"
  ]
}